metamoth/__init__.py
metamoth/artist.py
metamoth/audio.py
metamoth/chunks.py
metamoth/comments.py
metamoth/config.py
metamoth/enums.py
metamoth/mediainfo.py
metamoth/metadata.py
metamoth/metamoth.py
metamoth/parsing.py
metamoth/py.typed
metamoth-1.2.2.dist-info/METADATA
metamoth-1.2.2.dist-info/WHEEL
metamoth-1.2.2.dist-info/licenses/AUTHORS.rst
metamoth-1.2.2.dist-info/licenses/LICENSE
metamoth-1.2.2.dist-info/RECORD
