Metadata-Version: 2.3
Name: metamoth
Version: 1.2.2
Summary: Simple Python utility to parse AudioMoth metadata
Author-email: Santiago Martinez Balvanera <santiago.balvanera.20@ucl.ac.uk>
License: MIT license
License-File: AUTHORS.rst
License-File: LICENSE
Requires-Python: >=3.7
